{
  "@xmlns": "http://www.isotc211.org/2005/gmd",
  "@xmlns:functx": "http://www.functx.com",
  "@xmlns:gco": "http://www.isotc211.org/2005/gco",
  "@xmlns:geonet": "http://www.fao.org/geonetwork",
  "@xmlns:gfc": "http://www.isotc211.org/2005/gfc",
  "@xmlns:gmd": "http://www.isotc211.org/2005/gmd",
  "@xmlns:gmi": "http://www.isotc211.org/2005/gmi",
  "@xmlns:gml": "http://www.opengis.net/gml/3.2",
  "@xmlns:gmx": "http://www.isotc211.org/2005/gmx",
  "@xmlns:gsr": "http://www.isotc211.org/2005/gsr",
  "@xmlns:gss": "http://www.isotc211.org/2005/gss",
  "@xmlns:gts": "http://www.isotc211.org/2005/gts",
  "@xmlns:srv": "http://www.isotc211.org/2005/srv",
  "@xmlns:xlink": "http://www.w3.org/1999/xlink",
  "@xmlns:xsi": "http://www.w3.org/2001/XMLSchema-instance",
  "@xsi:schemaLocation": "http://www.isotc211.org/2005/gmd http://nap.geogratis.gc.ca/metadata/tools/schemas/metadata/can-cgsb-171.100-2009-a/gmd/gmd.xsd http://www.isotc211.org/2005/srv http://nap.geogratis.gc.ca/metadata/tools/schemas/metadata/can-cgsb-171.100-2009-a/srv/srv.xsd http://www.geconnections.org/nap/napMetadataTools/napXsd/napm http://nap.geogratis.gc.ca/metadata/tools/schemas/metadata/can-cgsb-171.100-2009-a/napm/napm.xsd",
  "gmd:fileIdentifier": {"gco:CharacterString":   {
    "@xmlns:gco": "http://www.isotc211.org/2005/gco",
    "#text": "a8b68ba4-c3d9-707f-a866-1aa53e7f0ae6"
  }},
  "gmd:language":   {
    "@xsi:type": "gmd:PT_FreeText_PropertyType",
    "gco:CharacterString":     {
      "@xmlns:gco": "http://www.isotc211.org/2005/gco",
      "#text": "eng; CAN"
    },
    "gmd:PT_FreeText": {"gmd:textGroup": {"gmd:LocalisedCharacterString":     {
      "@locale": "#fra",
      "#text": "fra; CAN"
    }}}
  },
  "gmd:characterSet": {"gmd:MD_CharacterSetCode":   {
    "@codeList": "http://nap.geogratis.gc.ca/metadata/register/napMetadataRegister.xml#IC_95",
    "@codeListValue": "RI_458",
    "#text": "utf8; utf8"
  }},
  "gmd:hierarchyLevel": {"gmd:MD_ScopeCode":   {
    "@codeList": "http://nap.geogratis.gc.ca/metadata/register/napMetadataRegister.xml#IC_108",
    "@codeListValue": "RI_622",
    "#text": "dataset; jeuDonnées"
  }},
  "gmd:contact":   [
    {"gmd:CI_ResponsibleParty":     {
      "gmd:individualName":       {
        "@xmlns:xsi": "http://www.w3.org/2001/XMLSchema-instance",
        "@xsi:type": "gmd:PT_FreeText_PropertyType",
        "gco:CharacterString":         {
          "@xmlns:gco": "http://www.isotc211.org/2005/gco",
          "#text": "Gavin Manson"
        },
        "gmd:PT_FreeText": {"gmd:textGroup": {"gmd:LocalisedCharacterString":         {
          "@locale": "#fra",
          "#text": "Gavin Manson"
        }}}
      },
      "gmd:organisationName":       {
        "@xmlns:xsi": "http://www.w3.org/2001/XMLSchema-instance",
        "@xsi:type": "gmd:PT_FreeText_PropertyType",
        "gco:CharacterString":         {
          "@xmlns:gco": "http://www.isotc211.org/2005/gco",
          "#text": "Government of Canada; Natural Resources Canada; Geological Survey of Canada - GSC Atlantique"
        },
        "gmd:PT_FreeText": {"gmd:textGroup": {"gmd:LocalisedCharacterString":         {
          "@locale": "#fra",
          "#text": "Gouvernement du Canada; Ressources naturelles Canada; Commission géologique du Canada - CGC Atlantique"
        }}}
      },
      "gmd:positionName":       {
        "@xmlns:xsi": "http://www.w3.org/2001/XMLSchema-instance",
        "@xsi:type": "gmd:PT_FreeText_PropertyType",
        "gco:CharacterString":         {
          "@xmlns:gco": "http://www.isotc211.org/2005/gco",
          "#text": "Coastal Geologist"
        },
        "gmd:PT_FreeText": {"gmd:textGroup": {"gmd:LocalisedCharacterString":         {
          "@locale": "#fra",
          "#text": "Géologue côtier"
        }}}
      },
      "gmd:contactInfo": {"gmd:CI_Contact":       {
        "gmd:phone": {"gmd:CI_Telephone": {"gmd:voice":         {
          "@xmlns:xsi": "http://www.w3.org/2001/XMLSchema-instance",
          "@xsi:type": "gmd:PT_FreeText_PropertyType",
          "gco:CharacterString":           {
            "@xmlns:gco": "http://www.isotc211.org/2005/gco",
            "#text": "voice; +01-902-426-3144"
          },
          "gmd:PT_FreeText": {"gmd:textGroup": {"gmd:LocalisedCharacterString":           {
            "@locale": "#fra",
            "#text": "voix; +01-902-426-3144"
          }}}
        }}},
        "gmd:address": {"gmd:CI_Address":         {
          "gmd:deliveryPoint":           {
            "@xmlns:xsi": "http://www.w3.org/2001/XMLSchema-instance",
            "@xsi:type": "PT_FreeText_PropertyType",
            "gco:CharacterString":             {
              "@xmlns:gco": "http://www.isotc211.org/2005/gco",
              "#text": "1 Challenger Drive"
            },
            "gmd:PT_FreeText": {"gmd:textGroup": {"gmd:LocalisedCharacterString":             {
              "@locale": "#fra",
              "#text": "1 Challenger Drive"
            }}}
          },
          "gmd:city":           {
            "@xmlns:xsi": "http://www.w3.org/2001/XMLSchema-instance",
            "@xsi:type": "PT_FreeText_PropertyType",
            "gco:CharacterString":             {
              "@xmlns:gco": "http://www.isotc211.org/2005/gco",
              "#text": "Dartmouth"
            },
            "gmd:PT_FreeText": {"gmd:textGroup": {"gmd:LocalisedCharacterString":             {
              "@locale": "#fra",
              "#text": "Dartmouth"
            }}}
          },
          "gmd:administrativeArea":           {
            "@xmlns:xsi": "http://www.w3.org/2001/XMLSchema-instance",
            "@xsi:type": "gmd:PT_FreeText_PropertyType",
            "gco:CharacterString":             {
              "@xmlns:gco": "http://www.isotc211.org/2005/gco",
              "#text": "Nova Scotia"
            },
            "gmd:PT_FreeText": {"gmd:textGroup": {"gmd:LocalisedCharacterString":             {
              "@locale": "#fra",
              "#text": "Nouvelle-Écosse"
            }}}
          },
          "gmd:country":           {
            "@xmlns:xsi": "http://www.w3.org/2001/XMLSchema-instance",
            "@xsi:type": "PT_FreeText_PropertyType",
            "gco:CharacterString":             {
              "@xmlns:gco": "http://www.isotc211.org/2005/gco",
              "#text": "Canada"
            },
            "gmd:PT_FreeText": {"gmd:textGroup": {"gmd:LocalisedCharacterString":             {
              "@locale": "#fra",
              "#text": "Canada"
            }}}
          },
          "gmd:electronicMailAddress":           {
            "@xmlns:xsi": "http://www.w3.org/2001/XMLSchema-instance",
            "@xsi:type": "PT_FreeText_PropertyType",
            "gco:CharacterString":             {
              "@xmlns:gco": "http://www.isotc211.org/2005/gco",
              "#text": "gavin.manson@canada.ca"
            },
            "gmd:PT_FreeText": {"gmd:textGroup": {"gmd:LocalisedCharacterString":             {
              "@locale": "#fra",
              "#text": "gavin.manson@canada.ca"
            }}}
          }
        }}
      }},
      "gmd:role": {"gmd:CI_RoleCode":       {
        "@codeList": "http://nap.geogratis.gc.ca/metadata/register/napMetadataRegister.xml#IC_90",
        "@codeListValue": "RI_418",
        "#text": "author; auteur"
      }}
    }},
    {"gmd:CI_ResponsibleParty":     {
      "gmd:organisationName":       {
        "@xmlns:xsi": "http://www.w3.org/2001/XMLSchema-instance",
        "@xsi:type": "gmd:PT_FreeText_PropertyType",
        "gco:CharacterString":         {
          "@xmlns:gco": "http://www.isotc211.org/2005/gco",
          "#text": "Government of Canada; Natural Resources Canada; Geological Survey of Canada"
        },
        "gmd:PT_FreeText": {"gmd:textGroup": {"gmd:LocalisedCharacterString":         {
          "@locale": "#fra",
          "#text": "Gouvernement du Canada; Ressources naturelles Canada; Commission géologique du Canada"
        }}}
      },
      "gmd:contactInfo": {"gmd:CI_Contact": {"gmd:address": {"gmd:CI_Address": {"gmd:electronicMailAddress":       {
        "@xmlns:xsi": "http://www.w3.org/2001/XMLSchema-instance",
        "@xsi:type": "gmd:PT_FreeText_PropertyType",
        "gco:CharacterString":         {
          "@xmlns:gco": "http://www.isotc211.org/2005/gco",
          "#text": "nrcan.gsc-geosciencedata-donneesgeoscience-cgc.rncan@canada.ca"
        },
        "gmd:PT_FreeText": {"gmd:textGroup": {"gmd:LocalisedCharacterString":         {
          "@locale": "#fra",
          "#text": "nrcan.gsc-geosciencedata-donneesgeoscience-cgc.rncan@canada.ca"
        }}}
      }}}}},
      "gmd:role": {"gmd:CI_RoleCode":       {
        "@codeList": "http://nap.geogratis.gc.ca/metadata/register/napMetadataRegister.xml#IC_90",
        "@codeListValue": "RI_414",
        "#text": "pointOfContact; contact"
      }}
    }}
  ],
  "gmd:dateStamp": {"gco:DateTime":   {
    "@xmlns:gco": "http://www.isotc211.org/2005/gco",
    "#text": "2019-09-16T19:43:49"
  }},
  "gmd:metadataStandardName":   {
    "@xsi:type": "PT_FreeText_PropertyType",
    "gco:CharacterString":     {
      "@xmlns:gco": "http://www.isotc211.org/2005/gco",
      "#text": "North American Profile of ISO 19115:2003 - Geographic information - Metadata"
    },
    "gmd:PT_FreeText": {"gmd:textGroup": {"gmd:LocalisedCharacterString":     {
      "@locale": "#fra",
      "#text": "Profil nord-américain de la norme ISO 19115:2003 - Information géographique - Métadonnées"
    }}}
  },
  "gmd:metadataStandardVersion": {"gco:CharacterString":   {
    "@xmlns:gco": "http://www.isotc211.org/2005/gco",
    "#text": "CAN/CGSB-171.100-2009"
  }},
  "gmd:dataSetURI": {"gco:CharacterString":   {
    "@xmlns:gco": "http://www.isotc211.org/2005/gco",
    "#text": "https://doi.org/10.4095/314669"
  }},
  "gmd:locale": {"gmd:PT_Locale":   {
    "@id": "fra",
    "gmd:languageCode": {"gmd:LanguageCode":     {
      "@codeList": "http://nap.geogratis.gc.ca/metadata/register/napMetadataRegister.xml#IC_116",
      "@codeListValue": "fra",
      "#text": "French; Français"
    }},
    "gmd:country": {"gmd:Country":     {
      "@codeList": "http://nap.geogratis.gc.ca/metadata/register/napMetadataRegister.xml#IC_117",
      "@codeListValue": "CAN",
      "#text": "Canada; Canada"
    }},
    "gmd:characterEncoding": {"gmd:MD_CharacterSetCode":     {
      "@codeList": "http://nap.geogratis.gc.ca/metadata/register/napMetadataRegister.xml#IC_95",
      "@codeListValue": "RI_458",
      "#text": "utf8; utf8"
    }}
  }},
  "gmd:spatialRepresentationInfo": null,
  "gmd:referenceSystemInfo": {"gmd:MD_ReferenceSystem": {"gmd:referenceSystemIdentifier": {"gmd:RS_Identifier":   {
    "gmd:code": {"gco:CharacterString":     {
      "@xmlns:gco": "http://www.isotc211.org/2005/gco",
      "#text": "EPSG:4617"
    }},
    "gmd:codeSpace": {"gco:CharacterString":     {
      "@xmlns:gco": "http://www.isotc211.org/2005/gco",
      "#text": "http://www.epsg-registry.org/"
    }},
    "gmd:version": {"gco:CharacterString":     {
      "@xmlns:gco": "http://www.isotc211.org/2005/gco",
      "#text": "6.14"
    }}
  }}}},
  "gmd:identificationInfo": {"gmd:MD_DataIdentification":   {
    "gmd:citation": {"gmd:CI_Citation":     {
      "gmd:title":       {
        "@xmlns:xsi": "http://www.w3.org/2001/XMLSchema-instance",
        "@xsi:type": "gmd:PT_FreeText_PropertyType",
        "gco:CharacterString":         {
          "@xmlns:gco": "http://www.isotc211.org/2005/gco",
          "#text": "CanCoast Coastal Sensitivity Indices Version 2.5.6"
        },
        "gmd:PT_FreeText": {"gmd:textGroup": {"gmd:LocalisedCharacterString":         {
          "@locale": "#fra",
          "#text": "Base CanCoast sur les indices de sensibilité du littoral, version 2.5.6"
        }}}
      },
      "gmd:date":       [
        {"gmd:CI_Date":         {
          "gmd:date": {"gco:Date":           {
            "@xmlns:gco": "http://www.isotc211.org/2005/gco",
            "#text": "2019-05-16"
          }},
          "gmd:dateType": {"gmd:CI_DateTypeCode":           {
            "@codeList": "http://nap.geogratis.gc.ca/metadata/register/napMetadataRegister.xml#IC_87",
            "@codeListValue": "RI_367",
            "#text": "publication; publication"
          }}
        }},
        {"gmd:CI_Date":         {
          "gmd:date": {"gco:Date":           {
            "@xmlns:gco": "http://www.isotc211.org/2005/gco",
            "#text": "2019-05-10"
          }},
          "gmd:dateType": {"gmd:CI_DateTypeCode":           {
            "@codeList": "http://nap.geogratis.gc.ca/metadata/register/napMetadataRegister.xml#IC_87",
            "@codeListValue": "RI_366",
            "#text": "creation; création"
          }}
        }}
      ],
      "gmd:edition":       {
        "@xmlns:gco": "http://www.isotc211.org/2005/gco",
        "@gco:nilReason": "missing",
        "gco:CharacterString": null
      },
      "gmd:citedResponsibleParty":       [
        {"gmd:CI_ResponsibleParty":         {
          "gmd:individualName":           {
            "@xmlns:xsi": "http://www.w3.org/2001/XMLSchema-instance",
            "@xsi:type": "gmd:PT_FreeText_PropertyType",
            "gco:CharacterString":             {
              "@xmlns:gco": "http://www.isotc211.org/2005/gco",
              "#text": "Gavin Manson"
            },
            "gmd:PT_FreeText": {"gmd:textGroup": {"gmd:LocalisedCharacterString":             {
              "@locale": "#fra",
              "#text": "Gavin Manson"
            }}}
          },
          "gmd:organisationName":           {
            "@xmlns:xsi": "http://www.w3.org/2001/XMLSchema-instance",
            "@xsi:type": "gmd:PT_FreeText_PropertyType",
            "gco:CharacterString":             {
              "@xmlns:gco": "http://www.isotc211.org/2005/gco",
              "#text": "Government of Canada; Natural Resources Canada; Geological Survey of Canada - GSC Atlantique"
            },
            "gmd:PT_FreeText": {"gmd:textGroup": {"gmd:LocalisedCharacterString":             {
              "@locale": "#fra",
              "#text": "Gouvernement du Canada; Ressources naturelles Canada; Commission géologique du Canada - CGC Atlantique"
            }}}
          },
          "gmd:positionName":           {
            "@xmlns:xsi": "http://www.w3.org/2001/XMLSchema-instance",
            "@xsi:type": "gmd:PT_FreeText_PropertyType",
            "gco:CharacterString":             {
              "@xmlns:gco": "http://www.isotc211.org/2005/gco",
              "#text": "Coastal Geologist"
            },
            "gmd:PT_FreeText": {"gmd:textGroup": {"gmd:LocalisedCharacterString":             {
              "@locale": "#fra",
              "#text": "Géologue côtier"
            }}}
          },
          "gmd:contactInfo": {"gmd:CI_Contact":           {
            "gmd:phone": {"gmd:CI_Telephone": {"gmd:voice":             {
              "@xmlns:xsi": "http://www.w3.org/2001/XMLSchema-instance",
              "@xsi:type": "gmd:PT_FreeText_PropertyType",
              "gco:CharacterString":               {
                "@xmlns:gco": "http://www.isotc211.org/2005/gco",
                "#text": "voice; +01-902-426-3144"
              },
              "gmd:PT_FreeText": {"gmd:textGroup": {"gmd:LocalisedCharacterString":               {
                "@locale": "#fra",
                "#text": "voix; +01-902-426-3144"
              }}}
            }}},
            "gmd:address": {"gmd:CI_Address":             {
              "gmd:deliveryPoint":               {
                "@xmlns:xsi": "http://www.w3.org/2001/XMLSchema-instance",
                "@xsi:type": "PT_FreeText_PropertyType",
                "gco:CharacterString":                 {
                  "@xmlns:gco": "http://www.isotc211.org/2005/gco",
                  "#text": "1 Challenger Drive"
                },
                "gmd:PT_FreeText": {"gmd:textGroup": {"gmd:LocalisedCharacterString":                 {
                  "@locale": "#fra",
                  "#text": "1 Challenger Drive"
                }}}
              },
              "gmd:city":               {
                "@xmlns:xsi": "http://www.w3.org/2001/XMLSchema-instance",
                "@xsi:type": "PT_FreeText_PropertyType",
                "gco:CharacterString":                 {
                  "@xmlns:gco": "http://www.isotc211.org/2005/gco",
                  "#text": "Dartmouth"
                },
                "gmd:PT_FreeText": {"gmd:textGroup": {"gmd:LocalisedCharacterString":                 {
                  "@locale": "#fra",
                  "#text": "Dartmouth"
                }}}
              },
              "gmd:administrativeArea":               {
                "@xmlns:xsi": "http://www.w3.org/2001/XMLSchema-instance",
                "@xsi:type": "gmd:PT_FreeText_PropertyType",
                "gco:CharacterString":                 {
                  "@xmlns:gco": "http://www.isotc211.org/2005/gco",
                  "#text": "Nova Scotia"
                },
                "gmd:PT_FreeText": {"gmd:textGroup": {"gmd:LocalisedCharacterString":                 {
                  "@locale": "#fra",
                  "#text": "Nouvelle-Écosse"
                }}}
              },
              "gmd:country":               {
                "@xmlns:xsi": "http://www.w3.org/2001/XMLSchema-instance",
                "@xsi:type": "PT_FreeText_PropertyType",
                "gco:CharacterString":                 {
                  "@xmlns:gco": "http://www.isotc211.org/2005/gco",
                  "#text": "Canada"
                },
                "gmd:PT_FreeText": {"gmd:textGroup": {"gmd:LocalisedCharacterString":                 {
                  "@locale": "#fra",
                  "#text": "Canada"
                }}}
              },
              "gmd:electronicMailAddress":               {
                "@xmlns:xsi": "http://www.w3.org/2001/XMLSchema-instance",
                "@xsi:type": "PT_FreeText_PropertyType",
                "gco:CharacterString":                 {
                  "@xmlns:gco": "http://www.isotc211.org/2005/gco",
                  "#text": "gavin.manson@canada.ca"
                },
                "gmd:PT_FreeText": {"gmd:textGroup": {"gmd:LocalisedCharacterString":                 {
                  "@locale": "#fra",
                  "#text": "gavin.manson@canada.ca"
                }}}
              }
            }}
          }},
          "gmd:role": {"gmd:CI_RoleCode":           {
            "@codeList": "http://nap.geogratis.gc.ca/metadata/register/napMetadataRegister.xml#IC_90",
            "@codeListValue": "RI_415",
            "#text": "principalInvestigator; chercheurPrincipal"
          }}
        }},
        {"gmd:CI_ResponsibleParty":         {
          "gmd:individualName":           {
            "@xmlns:xsi": "http://www.w3.org/2001/XMLSchema-instance",
            "@xsi:type": "gmd:PT_FreeText_PropertyType",
            "gco:CharacterString":             {
              "@xmlns:gco": "http://www.isotc211.org/2005/gco",
              "#text": "Gavin Manson"
            },
            "gmd:PT_FreeText": {"gmd:textGroup": {"gmd:LocalisedCharacterString":             {
              "@locale": "#fra",
              "#text": "Gavin Manson"
            }}}
          },
          "gmd:organisationName":           {
            "@xmlns:xsi": "http://www.w3.org/2001/XMLSchema-instance",
            "@xsi:type": "gmd:PT_FreeText_PropertyType",
            "gco:CharacterString":             {
              "@xmlns:gco": "http://www.isotc211.org/2005/gco",
              "#text": "Government of Canada; Natural Resources Canada; Geological Survey of Canada - GSC Atlantique"
            },
            "gmd:PT_FreeText": {"gmd:textGroup": {"gmd:LocalisedCharacterString":             {
              "@locale": "#fra",
              "#text": "Gouvernement du Canada; Ressources naturelles Canada; Commission géologique du Canada - CGC Atlantique"
            }}}
          },
          "gmd:positionName":           {
            "@xmlns:xsi": "http://www.w3.org/2001/XMLSchema-instance",
            "@xsi:type": "gmd:PT_FreeText_PropertyType",
            "gco:CharacterString":             {
              "@xmlns:gco": "http://www.isotc211.org/2005/gco",
              "#text": "Coastal Geologist"
            },
            "gmd:PT_FreeText": {"gmd:textGroup": {"gmd:LocalisedCharacterString":             {
              "@locale": "#fra",
              "#text": "Géologue côtier"
            }}}
          },
          "gmd:contactInfo": {"gmd:CI_Contact":           {
            "gmd:phone": {"gmd:CI_Telephone": {"gmd:voice":             {
              "@xmlns:xsi": "http://www.w3.org/2001/XMLSchema-instance",
              "@xsi:type": "gmd:PT_FreeText_PropertyType",
              "gco:CharacterString":               {
                "@xmlns:gco": "http://www.isotc211.org/2005/gco",
                "#text": "voice; +01-902-426-3144"
              },
              "gmd:PT_FreeText": {"gmd:textGroup": {"gmd:LocalisedCharacterString":               {
                "@locale": "#fra",
                "#text": "voix; +01-902-426-3144"
              }}}
            }}},
            "gmd:address": {"gmd:CI_Address":             {
              "gmd:deliveryPoint":               {
                "@xmlns:xsi": "http://www.w3.org/2001/XMLSchema-instance",
                "@xsi:type": "PT_FreeText_PropertyType",
                "gco:CharacterString":                 {
                  "@xmlns:gco": "http://www.isotc211.org/2005/gco",
                  "#text": "1 Challenger Drive"
                },
                "gmd:PT_FreeText": {"gmd:textGroup": {"gmd:LocalisedCharacterString":                 {
                  "@locale": "#fra",
                  "#text": "1 Challenger Drive"
                }}}
              },
              "gmd:city":               {
                "@xmlns:xsi": "http://www.w3.org/2001/XMLSchema-instance",
                "@xsi:type": "PT_FreeText_PropertyType",
                "gco:CharacterString":                 {
                  "@xmlns:gco": "http://www.isotc211.org/2005/gco",
                  "#text": "Dartmouth"
                },
                "gmd:PT_FreeText": {"gmd:textGroup": {"gmd:LocalisedCharacterString":                 {
                  "@locale": "#fra",
                  "#text": "Dartmouth"
                }}}
              },
              "gmd:administrativeArea":               {
                "@xmlns:xsi": "http://www.w3.org/2001/XMLSchema-instance",
                "@xsi:type": "gmd:PT_FreeText_PropertyType",
                "gco:CharacterString":                 {
                  "@xmlns:gco": "http://www.isotc211.org/2005/gco",
                  "#text": "Nova Scotia"
                },
                "gmd:PT_FreeText": {"gmd:textGroup": {"gmd:LocalisedCharacterString":                 {
                  "@locale": "#fra",
                  "#text": "Nouvelle-Écosse"
                }}}
              },
              "gmd:country":               {
                "@xmlns:xsi": "http://www.w3.org/2001/XMLSchema-instance",
                "@xsi:type": "PT_FreeText_PropertyType",
                "gco:CharacterString":                 {
                  "@xmlns:gco": "http://www.isotc211.org/2005/gco",
                  "#text": "Canada"
                },
                "gmd:PT_FreeText": {"gmd:textGroup": {"gmd:LocalisedCharacterString":                 {
                  "@locale": "#fra",
                  "#text": "Canada"
                }}}
              },
              "gmd:electronicMailAddress":               {
                "@xmlns:xsi": "http://www.w3.org/2001/XMLSchema-instance",
                "@xsi:type": "PT_FreeText_PropertyType",
                "gco:CharacterString":                 {
                  "@xmlns:gco": "http://www.isotc211.org/2005/gco",
                  "#text": "gavin.manson@canada.ca"
                },
                "gmd:PT_FreeText": {"gmd:textGroup": {"gmd:LocalisedCharacterString":                 {
                  "@locale": "#fra",
                  "#text": "gavin.manson@canada.ca"
                }}}
              }
            }}
          }},
          "gmd:role": {"gmd:CI_RoleCode":           {
            "@codeList": "http://nap.geogratis.gc.ca/metadata/register/napMetadataRegister.xml#IC_90",
            "@codeListValue": "RI_413",
            "#text": "originator; auteur"
          }}
        }},
        {"gmd:CI_ResponsibleParty":         {
          "gmd:individualName":           {
            "@xmlns:xsi": "http://www.w3.org/2001/XMLSchema-instance",
            "@xsi:type": "gmd:PT_FreeText_PropertyType",
            "gco:CharacterString":             {
              "@xmlns:gco": "http://www.isotc211.org/2005/gco",
              "#text": "Gavin Manson"
            },
            "gmd:PT_FreeText": {"gmd:textGroup": {"gmd:LocalisedCharacterString":             {
              "@locale": "#fra",
              "#text": "Gavin Manson"
            }}}
          },
          "gmd:organisationName":           {
            "@xmlns:xsi": "http://www.w3.org/2001/XMLSchema-instance",
            "@xsi:type": "gmd:PT_FreeText_PropertyType",
            "gco:CharacterString":             {
              "@xmlns:gco": "http://www.isotc211.org/2005/gco",
              "#text": "Government of Canada; Natural Resources Canada; Geological Survey of Canada - GSC Atlantique"
            },
            "gmd:PT_FreeText": {"gmd:textGroup": {"gmd:LocalisedCharacterString":             {
              "@locale": "#fra",
              "#text": "Gouvernement du Canada; Ressources naturelles Canada; Commission géologique du Canada - CGC Atlantique"
            }}}
          },
          "gmd:positionName":           {
            "@xmlns:xsi": "http://www.w3.org/2001/XMLSchema-instance",
            "@xsi:type": "gmd:PT_FreeText_PropertyType",
            "gco:CharacterString":             {
              "@xmlns:gco": "http://www.isotc211.org/2005/gco",
              "#text": "Coastal Geologist"
            },
            "gmd:PT_FreeText": {"gmd:textGroup": {"gmd:LocalisedCharacterString":             {
              "@locale": "#fra",
              "#text": "Géologue côtier"
            }}}
          },
          "gmd:contactInfo": {"gmd:CI_Contact":           {
            "gmd:phone": {"gmd:CI_Telephone": {"gmd:voice":             {
              "@xmlns:xsi": "http://www.w3.org/2001/XMLSchema-instance",
              "@xsi:type": "gmd:PT_FreeText_PropertyType",
              "gco:CharacterString":               {
                "@xmlns:gco": "http://www.isotc211.org/2005/gco",
                "#text": "voice; +01-902-426-3144"
              },
              "gmd:PT_FreeText": {"gmd:textGroup": {"gmd:LocalisedCharacterString":               {
                "@locale": "#fra",
                "#text": "voix; +01-902-426-3144"
              }}}
            }}},
            "gmd:address": {"gmd:CI_Address":             {
              "gmd:deliveryPoint":               {
                "@xmlns:xsi": "http://www.w3.org/2001/XMLSchema-instance",
                "@xsi:type": "PT_FreeText_PropertyType",
                "gco:CharacterString":                 {
                  "@xmlns:gco": "http://www.isotc211.org/2005/gco",
                  "#text": "1 Challenger Drive"
                },
                "gmd:PT_FreeText": {"gmd:textGroup": {"gmd:LocalisedCharacterString":                 {
                  "@locale": "#fra",
                  "#text": "1 Challenger Drive"
                }}}
              },
              "gmd:city":               {
                "@xmlns:xsi": "http://www.w3.org/2001/XMLSchema-instance",
                "@xsi:type": "PT_FreeText_PropertyType",
                "gco:CharacterString":                 {
                  "@xmlns:gco": "http://www.isotc211.org/2005/gco",
                  "#text": "Dartmouth"
                },
                "gmd:PT_FreeText": {"gmd:textGroup": {"gmd:LocalisedCharacterString":                 {
                  "@locale": "#fra",
                  "#text": "Dartmouth"
                }}}
              },
              "gmd:administrativeArea":               {
                "@xmlns:xsi": "http://www.w3.org/2001/XMLSchema-instance",
                "@xsi:type": "gmd:PT_FreeText_PropertyType",
                "gco:CharacterString":                 {
                  "@xmlns:gco": "http://www.isotc211.org/2005/gco",
                  "#text": "Nova Scotia"
                },
                "gmd:PT_FreeText": {"gmd:textGroup": {"gmd:LocalisedCharacterString":                 {
                  "@locale": "#fra",
                  "#text": "Nouvelle-Écosse"
                }}}
              },
              "gmd:country":               {
                "@xmlns:xsi": "http://www.w3.org/2001/XMLSchema-instance",
                "@xsi:type": "PT_FreeText_PropertyType",
                "gco:CharacterString":                 {
                  "@xmlns:gco": "http://www.isotc211.org/2005/gco",
                  "#text": "Canada"
                },
                "gmd:PT_FreeText": {"gmd:textGroup": {"gmd:LocalisedCharacterString":                 {
                  "@locale": "#fra",
                  "#text": "Canada"
                }}}
              },
              "gmd:electronicMailAddress":               {
                "@xmlns:xsi": "http://www.w3.org/2001/XMLSchema-instance",
                "@xsi:type": "PT_FreeText_PropertyType",
                "gco:CharacterString":                 {
                  "@xmlns:gco": "http://www.isotc211.org/2005/gco",
                  "#text": "gavin.manson@canada.ca"
                },
                "gmd:PT_FreeText": {"gmd:textGroup": {"gmd:LocalisedCharacterString":                 {
                  "@locale": "#fra",
                  "#text": "gavin.manson@canada.ca"
                }}}
              }
            }}
          }},
          "gmd:role": {"gmd:CI_RoleCode":           {
            "@codeList": "http://nap.geogratis.gc.ca/metadata/register/napMetadataRegister.xml#IC_90",
            "@codeListValue": "RI_409",
            "#text": "custodian; conservateur"
          }}
        }},
        {"gmd:CI_ResponsibleParty":         {
          "gmd:organisationName":           {
            "@xmlns:xsi": "http://www.w3.org/2001/XMLSchema-instance",
            "@xsi:type": "gmd:PT_FreeText_PropertyType",
            "gco:CharacterString":             {
              "@xmlns:gco": "http://www.isotc211.org/2005/gco",
              "#text": "Government of Canada; Natural Resources Canada; Geological Survey of Canada"
            },
            "gmd:PT_FreeText": {"gmd:textGroup": {"gmd:LocalisedCharacterString":             {
              "@locale": "#fra",
              "#text": "Gouvernement du Canada; Ressources naturelles Canada; Commission géologique du Canada"
            }}}
          },
          "gmd:contactInfo": {"gmd:CI_Contact": {"gmd:address": {"gmd:CI_Address": {"gmd:electronicMailAddress":           {
            "@xmlns:xsi": "http://www.w3.org/2001/XMLSchema-instance",
            "@xsi:type": "gmd:PT_FreeText_PropertyType",
            "gco:CharacterString":             {
              "@xmlns:gco": "http://www.isotc211.org/2005/gco",
              "#text": "nrcan.gsc-geosciencedata-donneesgeoscience-cgc.rncan@canada.ca"
            },
            "gmd:PT_FreeText": {"gmd:textGroup": {"gmd:LocalisedCharacterString":             {
              "@locale": "#fra",
              "#text": "nrcan.gsc-geosciencedata-donneesgeoscience-cgc.rncan@canada.ca"
            }}}
          }}}}},
          "gmd:role": {"gmd:CI_RoleCode":           {
            "@codeList": "http://nap.geogratis.gc.ca/metadata/register/napMetadataRegister.xml#IC_90",
            "@codeListValue": "RI_414",
            "#text": "pointOfContact; contact"
          }}
        }}
      ],
      "gmd:presentationForm": {"gmd:CI_PresentationFormCode":       {
        "@codeList": "http://nap.geogratis.gc.ca/metadata/register/napMetadataRegister.xml#IC_89",
        "@codeListValue": "RI_391",
        "#text": "mapDigital;carteNumérique"
      }},
      "gmd:series": {"gmd:CI_Series": {"gmd:name": {"gco:CharacterString":       {
        "@xmlns:gco": "http://www.isotc211.org/2005/gco",
        "#text": "Open File"
      }}}},
      "gmd:otherCitationDetails": {"gco:CharacterString":       {
        "@xmlns:gco": "http://www.isotc211.org/2005/gco",
        "#text": "Manson, G.K., Couture, N.J, James, T.S., 2019. CanCoast 2.0: Data and Indices to Describe the Sensitivity of Canada's Marine Coasts to Changing Climate; Geological Survey of Canada, Open File 8551, 18 + ii p. https://doi.org/10.4095/314669"
      }}
    }},
    "gmd:abstract":     {
      "@xmlns:xsi": "http://www.w3.org/2001/XMLSchema-instance",
      "@xsi:type": "gmd:PT_FreeText_PropertyType",
      "gco:CharacterString":       {
        "@xmlns:gco": "http://www.isotc211.org/2005/gco",
        "#text": "CanCoast is a geospatial database of the physical characteristics of Canada's marine coasts. It includes both feature classes that are not expected to change through time, and feature classes that are expected to change as climate changes. CanCoast includes: wave-height change with sea ice (early and late 21st century); sea-level change (early and late century); ground ice content; coastal materials; tidal range; and backshore slope. These are mapped to a common high-resolution shoreline and used to calculate indices that show the coastal sensitivity of Canada's marine coasts in modelled early and late 21st century climates."
      },
      "gmd:PT_FreeText": {"gmd:textGroup": {"gmd:LocalisedCharacterString":       {
        "@locale": "#fra",
        "#text": "CanCoast est une base de données géospatiales sur les caractéristiques physiques du littoral maritime du Canada. Elle comprend à la fois des classes d'entités qui ne devraient pas changer au fil du temps et des classes d'entités qui devraient changer à mesure que le climat évolue. CanCoast comprend les données suivantes : le changement de la hauteur des vagues avec la glace de mer (début et fin du XXIe siècle); le changement du niveau de la mer (début et fin du siècle); la teneur en glace du sol; les matériaux côtiers; l'amplitude des marées; et la pente de l'arrière-plage. Ces données sont cartographiées sur un rivage commun à haute résolution et utilisées pour calculer des indices qui montrent la sensibilité des zones côtières du littoral maritime du Canada dans des climats modélisés du début et de la fin du XXIe siècle."
      }}}
    },
    "gmd:purpose":     {
      "@xmlns:xsi": "http://www.w3.org/2001/XMLSchema-instance",
      "@xsi:type": "gmd:PT_FreeText_PropertyType",
      "gco:CharacterString":       {
        "@xmlns:gco": "http://www.isotc211.org/2005/gco",
        "#text": "The purpose of this feature class is to calculate and map the changing sensitivity of Canada's marine coasts to changing climate. Two indices of sensitivity are provided. The first uses data representing early 21st century sensitivity and the second uses data representing late 21st century sensitivity. The difference between the early and late 21st century sensitivities giving the projected change in the sensitivity of Canada's marine coasts by 2100 is also provided."
      },
      "gmd:PT_FreeText": {"gmd:textGroup": {"gmd:LocalisedCharacterString":       {
        "@locale": "#fra",
        "#text": "La présente classe d'entités sert à mesurer et à cartographier la variation de la sensibilité du littoral canadien aux changements climatiques. Deux indices de sensibilité sont donnés : le premier repose sur les données représentant la sensibilité au début du XXIe siècle et le second, celles pour la fin du XXIe siècle. Nous avons calculé la différence entre ces deux sensibilités, afin d'obtenir le changement prévu de la sensibilité du littoral canadien d'ici 2100."
      }}}
    },
    "gmd:credit":     {
      "@xmlns:xsi": "http://www.w3.org/2001/XMLSchema-instance",
      "@xsi:type": "PT_FreeText_PropertyType",
      "gco:CharacterString":       {
        "@xmlns:gco": "http://www.isotc211.org/2005/gco",
        "#text": "Funding for CanCoast was provided by the Climate Change Geoscience Program of the Lands and Minerals Sector of Natural Resources Canada under the Supporting Adaptation in Coastal Regions project. Additional funding was provided by the Climate Change Impacts and Adaptations Division of Natural Resources Canada."
      },
      "gmd:PT_FreeText": {"gmd:textGroup": {"gmd:LocalisedCharacterString":       {
        "@locale": "#fra",
        "#text": "Le financement de CanCoast a été fourni par le Programme de géoscience des changements climatiques du Secteur des terres et des minéraux de Ressources naturelles Canada dans le cadre du projet Appuyer l'adaptation dans les régions côtières. La Division des impacts et de l'adaptation liés aux changements climatiques de Ressources naturelles Canada a fourni un financement supplémentaire."
      }}}
    },
    "gmd:status": {"gmd:MD_ProgressCode":     {
      "@codeList": "http://nap.geogratis.gc.ca/metadata/register/napMetadataRegister.xml#IC_106",
      "@codeListValue": "RI_593",
      "#text": "completed; complété"
    }},
    "gmd:resourceMaintenance": {"gmd:MD_MaintenanceInformation": {"gmd:maintenanceAndUpdateFrequency": {"gmd:MD_MaintenanceFrequencyCode":     {
      "@codeList": "http://nap.geogratis.gc.ca/metadata/register/napMetadataRegister.xml#IC_102",
      "@codeListValue": "RI_542",
      "#text": "notPlanned; nonPlanifié"
    }}}},
    "gmd:graphicOverview": {"gmd:MD_BrowseGraphic": {"gmd:fileName":     {
      "@xmlns:xsi": "http://www.w3.org/2001/XMLSchema-instance",
      "@xsi:type": "PT_FreeText_PropertyType",
      "gco:CharacterString":       {
        "@xmlns:gco": "http://www.isotc211.org/2005/gco",
        "#text": "http://gin.gw-info.net/service/ngwds/en/metadata/nap/thumbnails/a8b68ba4-c3d9-707f-a866-1aa53e7f0ae6.jpg"
      },
      "gmd:PT_FreeText": {"gmd:textGroup": {"gmd:LocalisedCharacterString":       {
        "@locale": "#fra",
        "#text": "http://gin.gw-info.net/service/ngwds/en/metadata/nap/thumbnails/a8b68ba4-c3d9-707f-a866-1aa53e7f0ae6.jpg"
      }}}
    }}},
    "gmd:descriptiveKeywords":     [
      {"gmd:MD_Keywords":       {
        "gmd:keyword":         {
          "@xmlns:xsi": "http://www.w3.org/2001/XMLSchema-instance",
          "@xsi:type": "gmd:PT_FreeText_PropertyType",
          "gco:CharacterString":           {
            "@xmlns:gco": "http://www.isotc211.org/2005/gco",
            "#text": "Coastal and Marine Geology"
          },
          "gmd:PT_FreeText": {"gmd:textGroup": {"gmd:LocalisedCharacterString":           {
            "@locale": "#fra",
            "#text": "Géologie côtière et marine"
          }}}
        },
        "gmd:type": {"gmd:MD_KeywordTypeCode":         {
          "@codeList": "http://nap.geogratis.gc.ca/metadata/register/napMetadataRegister.xml#IC_101",
          "@codeListValue": "RI_528",
          "#text": "theme; thème"
        }},
        "gmd:thesaurusName": {"gmd:CI_Citation":         {
          "gmd:title":           {
            "@xmlns:xsi": "http://www.w3.org/2001/XMLSchema-instance",
            "@xsi:type": "gmd:PT_FreeText_PropertyType",
            "gco:CharacterString":             {
              "@xmlns:gco": "http://www.isotc211.org/2005/gco",
              "#text": "GSC Keywords Vocabulary - Thesaurus"
            },
            "gmd:PT_FreeText": {"gmd:textGroup": {"gmd:LocalisedCharacterString":             {
              "@locale": "#fra",
              "#text": "Thésaurus - vocabulaire de mots-clé de la CGC"
            }}}
          },
          "gmd:date":           [
            {"gmd:CI_Date":             {
              "gmd:date": {"gco:Date":               {
                "@xmlns:gco": "http://www.isotc211.org/2005/gco",
                "#text": "2016-12-01"
              }},
              "gmd:dateType": {"gmd:CI_DateTypeCode":               {
                "@codeList": "http://nap.geogratis.gc.ca/metadata/register/napMetadataRegister.xml#IC_87",
                "@codeListValue": "RI_366",
                "#text": "creation; création"
              }}
            }},
            {"gmd:CI_Date":             {
              "gmd:date": {"gco:Date":               {
                "@xmlns:gco": "http://www.isotc211.org/2005/gco",
                "#text": "2016-12-01"
              }},
              "gmd:dateType": {"gmd:CI_DateTypeCode":               {
                "@codeList": "http://nap.geogratis.gc.ca/metadata/register/napMetadataRegister.xml#IC_87",
                "@codeListValue": "RI_367",
                "#text": "publication; publication"
              }}
            }}
          ],
          "gmd:citedResponsibleParty": {"gmd:CI_ResponsibleParty":           {
            "gmd:organisationName":             {
              "@xmlns:xsi": "http://www.w3.org/2001/XMLSchema-instance",
              "@xsi:type": "gmd:PT_FreeText_PropertyType",
              "gco:CharacterString":               {
                "@xmlns:gco": "http://www.isotc211.org/2005/gco",
                "#text": "Government of Canada; Natural Resources Canada; Geological Survey of Canada"
              },
              "gmd:PT_FreeText": {"gmd:textGroup": {"gmd:LocalisedCharacterString":               {
                "@locale": "#fra",
                "#text": "Gouvernement du Canada; Ressources naturelles Canada; Commission géologique du Canada"
              }}}
            },
            "gmd:contactInfo": {"gmd:CI_Contact": {"gmd:onlineResource": {"gmd:CI_OnlineResource":             {
              "gmd:linkage": {"gmd:URL": "http://ngwd-bdnes.cits.nrcan.gc.ca/Reference/uri-cgi/classifierScheme/ca.geosc_gsc/keyword"},
              "gmd:protocol":               {
                "@xmlns:xsi": "http://www.w3.org/2001/XMLSchema-instance",
                "@xsi:type": "PT_FreeText_PropertyType",
                "gco:CharacterString":                 {
                  "@xmlns:gco": "http://www.isotc211.org/2005/gco",
                  "#text": "http"
                },
                "gmd:PT_FreeText": {"gmd:textGroup": {"gmd:LocalisedCharacterString": "http"}}
              }
            }}}},
            "gmd:role": {"gmd:CI_RoleCode":             {
              "@codeList": "http://nap.geogratis.gc.ca/metadata/register/napMetadataRegister.xml#IC_90",
              "@codeListValue": "RI_409",
              "#text": "custodian; conservateur"
            }}
          }}
        }}
      }},
      {"gmd:MD_Keywords":       {
        "gmd:keyword":         {
          "@xmlns:xsi": "http://www.w3.org/2001/XMLSchema-instance",
          "@xsi:type": "gmd:PT_FreeText_PropertyType",
          "gco:CharacterString":           {
            "@xmlns:gco": "http://www.isotc211.org/2005/gco",
            "#text": "sensitivity"
          },
          "gmd:PT_FreeText": {"gmd:textGroup": {"gmd:LocalisedCharacterString":           {
            "@locale": "#fra",
            "#text": "sensibilité"
          }}}
        },
        "gmd:type": {"gmd:MD_KeywordTypeCode":         {
          "@codeList": "http://nap.geogratis.gc.ca/metadata/register/napMetadataRegister.xml#IC_101",
          "@codeListValue": "RI_528",
          "#text": "theme; thème"
        }},
        "gmd:thesaurusName": {"gmd:CI_Citation":         {
          "gmd:title":           {
            "@xmlns:xsi": "http://www.w3.org/2001/XMLSchema-instance",
            "@xsi:type": "gmd:PT_FreeText_PropertyType",
            "gco:CharacterString":             {
              "@xmlns:gco": "http://www.isotc211.org/2005/gco",
              "#text": "NRCan - GSC - Coastal domain - Keywords list"
            },
            "gmd:PT_FreeText": {"gmd:textGroup": {"gmd:LocalisedCharacterString":             {
              "@locale": "#fra",
              "#text": "Liste de mots-clés - RNCan - CGC - Domain côtier"
            }}}
          },
          "gmd:date":           [
            {"gmd:CI_Date":             {
              "gmd:date": {"gco:Date":               {
                "@xmlns:gco": "http://www.isotc211.org/2005/gco",
                "#text": "2009-01-01"
              }},
              "gmd:dateType": {"gmd:CI_DateTypeCode":               {
                "@codeList": "http://nap.geogratis.gc.ca/metadata/register/napMetadataRegister.xml#IC_87",
                "@codeListValue": "RI_366",
                "#text": "creation; création"
              }}
            }},
            {"gmd:CI_Date":             {
              "gmd:date": {"gco:Date":               {
                "@xmlns:gco": "http://www.isotc211.org/2005/gco",
                "#text": "2016-12-01"
              }},
              "gmd:dateType": {"gmd:CI_DateTypeCode":               {
                "@codeList": "http://nap.geogratis.gc.ca/metadata/register/napMetadataRegister.xml#IC_87",
                "@codeListValue": "RI_367",
                "#text": "publication; publication"
              }}
            }}
          ],
          "gmd:citedResponsibleParty": {"gmd:CI_ResponsibleParty":           {
            "gmd:organisationName":             {
              "@xmlns:xsi": "http://www.w3.org/2001/XMLSchema-instance",
              "@xsi:type": "gmd:PT_FreeText_PropertyType",
              "gco:CharacterString":               {
                "@xmlns:gco": "http://www.isotc211.org/2005/gco",
                "#text": "Government of Canada; Natural Resources Canada; Geological Survey of Canada"
              },
              "gmd:PT_FreeText": {"gmd:textGroup": {"gmd:LocalisedCharacterString":               {
                "@locale": "#fra",
                "#text": "Gouvernement du Canada; Ressources naturelles Canada; Commission géologique du Canada"
              }}}
            },
            "gmd:role": {"gmd:CI_RoleCode":             {
              "@codeList": "http://nap.geogratis.gc.ca/metadata/register/napMetadataRegister.xml#IC_90",
              "@codeListValue": "RI_409",
              "#text": "custodian; conservateur"
            }}
          }}
        }}
      }},
      {"gmd:MD_Keywords":       {
        "gmd:keyword":         {
          "@xmlns:xsi": "http://www.w3.org/2001/XMLSchema-instance",
          "@xsi:type": "gmd:PT_FreeText_PropertyType",
          "gco:CharacterString":           {
            "@xmlns:gco": "http://www.isotc211.org/2005/gco",
            "#text": "Coasts"
          },
          "gmd:PT_FreeText": {"gmd:textGroup": {"gmd:LocalisedCharacterString":           {
            "@locale": "#fra",
            "#text": "Littoral"
          }}}
        },
        "gmd:type": {"gmd:MD_KeywordTypeCode":         {
          "@codeList": "http://nap.geogratis.gc.ca/metadata/register/napMetadataRegister.xml#IC_101",
          "@codeListValue": "RI_528",
          "#text": "theme; thème"
        }},
        "gmd:thesaurusName": {"gmd:CI_Citation":         {
          "gmd:title":           {
            "@xmlns:xsi": "http://www.w3.org/2001/XMLSchema-instance",
            "@xsi:type": "gmd:PT_FreeText_PropertyType",
            "gco:CharacterString":             {
              "@xmlns:gco": "http://www.isotc211.org/2005/gco",
              "#text": "Government of Canada Core Subject Thesaurus"
            },
            "gmd:PT_FreeText": {"gmd:textGroup": {"gmd:LocalisedCharacterString":             {
              "@locale": "#fra",
              "#text": "Thésaurus des sujets de base du gouvernement du Canada"
            }}}
          },
          "gmd:date":           [
            {"gmd:CI_Date":             {
              "gmd:date": {"gco:Date":               {
                "@xmlns:gco": "http://www.isotc211.org/2005/gco",
                "#text": "2004"
              }},
              "gmd:dateType": {"gmd:CI_DateTypeCode":               {
                "@codeList": "http://nap.geogratis.gc.ca/metadata/register/napMetadataRegister.xml#IC_87",
                "@codeListValue": "RI_366",
                "#text": "creation;création"
              }}
            }},
            {"gmd:CI_Date":             {
              "gmd:date": {"gco:Date":               {
                "@xmlns:gco": "http://www.isotc211.org/2005/gco",
                "#text": "2016-07-04"
              }},
              "gmd:dateType": {"gmd:CI_DateTypeCode":               {
                "@codeList": "http://nap.geogratis.gc.ca/metadata/register/napMetadataRegister.xml#IC_87",
                "@codeListValue": "RI_367",
                "#text": "publication;publication"
              }}
            }}
          ],
          "gmd:citedResponsibleParty": {"gmd:CI_ResponsibleParty":           {
            "gmd:organisationName":             {
              "@xmlns:xsi": "http://www.w3.org/2001/XMLSchema-instance",
              "@xsi:type": "gmd:PT_FreeText_PropertyType",
              "gco:CharacterString":               {
                "@xmlns:gco": "http://www.isotc211.org/2005/gco",
                "#text": "Government of Canada; Library and Archives Canada"
              },
              "gmd:PT_FreeText": {"gmd:textGroup": {"gmd:LocalisedCharacterString":               {
                "@locale": "#fra",
                "#text": "Gouvernement du Canada; Bibliothèque et Archives Canada"
              }}}
            },
            "gmd:role": {"gmd:CI_RoleCode":             {
              "@codeList": "http://nap.geogratis.gc.ca/metadata/register/napMetadataRegister.xml#IC_90",
              "@codeListValue": "RI_409",
              "#text": "custodian; conservateur"
            }}
          }}
        }}
      }}
    ],
    "gmd:resourceConstraints":     [
      {"gmd:MD_Constraints": {"gmd:useLimitation":       {
        "@xmlns:xsi": "http://www.w3.org/2001/XMLSchema-instance",
        "@xsi:type": "gmd:PT_FreeText_PropertyType",
        "gco:CharacterString":         {
          "@xmlns:gco": "http://www.isotc211.org/2005/gco",
          "#text": "Her Majesty the Queen in Right of Canada 2018"
        },
        "gmd:PT_FreeText": {"gmd:textGroup": {"gmd:LocalisedCharacterString":         {
          "@locale": "#fra",
          "#text": "Sa Majesté la Reine du chef du Canada 2018"
        }}}
      }}},
      {"gmd:MD_LegalConstraints":       {
        "gmd:useLimitation":         {
          "@xmlns:xsi": "http://www.w3.org/2001/XMLSchema-instance",
          "@xsi:type": "gmd:PT_FreeText_PropertyType",
          "gco:CharacterString":           {
            "@xmlns:gco": "http://www.isotc211.org/2005/gco",
            "#text": "Open Government Licence - Canada (http://open.canada.ca/en/open-government-licence-canada)"
          },
          "gmd:PT_FreeText": {"gmd:textGroup": {"gmd:LocalisedCharacterString":           {
            "@locale": "#fra",
            "#text": "Licence du gouvernement ouvert - Canada (http://ouvert.canada.ca/fr/licence-du-gouvernement-ouvert-canada)"
          }}}
        },
        "gmd:accessConstraints": {"gmd:MD_RestrictionCode":         {
          "@codeList": "http://nap.geogratis.gc.ca/metadata/register/napMetadataRegister.xml#IC_107",
          "@codeListValue": "RI_606",
          "#text": "license; licence"
        }},
        "gmd:useConstraints": {"gmd:MD_RestrictionCode":         {
          "@codeList": "http://nap.geogratis.gc.ca/metadata/register/napMetadataRegister.xml#IC_107",
          "@codeListValue": "RI_609",
          "#text": "otherRestrictions; autresRestrictions"
        }}
      }}
    ],
    "gmd:spatialRepresentationType": {"gmd:MD_SpatialRepresentationTypeCode":     {
      "@codeList": "http://nap.geogratis.gc.ca/metadata/register/napMetadataRegister.xml#IC_109",
      "@codeListValue": "RI_635",
      "#text": "vector; vecteur"
    }},
    "gmd:language": {"gco:CharacterString":     {
      "@xmlns:gco": "http://www.isotc211.org/2005/gco",
      "#text": "eng; CAN"
    }},
    "gmd:characterSet": {"gmd:MD_CharacterSetCode":     {
      "@codeList": "http://nap.geogratis.gc.ca/metadata/register/napMetadataRegister.xml#IC_95",
      "@codeListValue": "RI_458",
      "#text": "utf8; utf8"
    }},
    "gmd:topicCategory": {"gmd:MD_TopicCategoryCode": "geoscientificInformation"},
    "gmd:extent": {"gmd:EX_Extent":     {
      "gmd:description":       {
        "@xmlns:xsi": "http://www.w3.org/2001/XMLSchema-instance",
        "@xsi:type": "gmd:PT_FreeText_PropertyType",
        "gco:CharacterString":         {
          "@xmlns:gco": "http://www.isotc211.org/2005/gco",
          "#text": "Canada's marine coasts."
        },
        "gmd:PT_FreeText": {"gmd:textGroup": {"gmd:LocalisedCharacterString":         {
          "@locale": "#fra",
          "#text": "Le littoral maritime du Canada."
        }}}
      },
      "gmd:geographicElement": {"gmd:EX_GeographicBoundingBox":       {
        "gmd:extentTypeCode": {"gco:Boolean":         {
          "@xmlns:gco": "http://www.isotc211.org/2005/gco",
          "#text": "1"
        }},
        "gmd:westBoundLongitude": {"gco:Decimal":         {
          "@xmlns:gco": "http://www.isotc211.org/2005/gco",
          "#text": "-141.000000000"
        }},
        "gmd:eastBoundLongitude": {"gco:Decimal":         {
          "@xmlns:gco": "http://www.isotc211.org/2005/gco",
          "#text": "-52.620000000"
        }},
        "gmd:southBoundLatitude": {"gco:Decimal":         {
          "@xmlns:gco": "http://www.isotc211.org/2005/gco",
          "#text": "40.390000000"
        }},
        "gmd:northBoundLatitude": {"gco:Decimal":         {
          "@xmlns:gco": "http://www.isotc211.org/2005/gco",
          "#text": "83.140000000"
        }}
      }},
      "gmd:temporalElement": {"gmd:EX_TemporalExtent": {"gmd:extent": {"gml:TimePeriod":       {
        "@xmlns:gml": "http://www.opengis.net/gml/3.2",
        "@gml:id": "time_per1",
        "gml:beginPosition": "2010-12-31",
        "gml:endPosition": "2011-12-31"
      }}}}
    }},
    "gmd:supplementalInformation":     {
      "@xmlns:xsi": "http://www.w3.org/2001/XMLSchema-instance",
      "@xsi:type": "gmd:PT_FreeText_PropertyType",
      "gco:CharacterString":       {
        "@xmlns:gco": "http://www.isotc211.org/2005/gco",
        "#text": "All input data sources were developed by the Geological Survey of Canada, Natural Resources Canada. The early and late 21st century indices were calculated from the scores of the input data using a µ -statistics approach (Morales et al., 2008; Wittkowski et al., 2004). The coastal sensitivity index (CSI) contains a score for each shoreline segment based on its coastal type and the sensitivity of that type relative to other coastal types. The change in sensitivity is the early 21st century CSI subtracted from the late 21st century CSI. Additional information are available through GeoScan. Morales, J.F., Song, T., Auerbach, A.D., and Wittkowski, K.M., 2008. Phenotyping genetic diseases using an extension of &#956;-scores for Multivariate Data. Statistical Applications in Genetics and Molecular Biology, 7: 1-18 DOI: 10.2202/1544-6115.1372 Wittkowski, K. M., Lee, E., Nussbaum, R., Chamian, F. N., & Krueger, J. G. (2004). Combining several ordinal measures in clinical studies. Statistics in Medicine, 23: 1579-1592. https://doi.org/10.1002/sim.1778."
      },
      "gmd:PT_FreeText": {"gmd:textGroup": {"gmd:LocalisedCharacterString":       {
        "@locale": "#fra",
        "#text": "Toutes les sources de données d'entrée ont été conçues par la Commission géologique du Canada de Ressources naturelles CanadaLes indices du début et de la fin du 21ème siècle ont été calculés à partir des scores des données d'entrée en utilisant une approche µ-statistique (Morales et al., 2008; Wittkowski et al., 2004). L'indice de sensibilité du littoral (CSI) contient un score pour chaque segment de rivage en fonction de son type de côtes et de la sensibilité de ce type par rapport à d'autres types côtiers. La variation de la sensibilité est obtenue en soustrayant l'ISC du début du XXIe siècle de celui de la fin du XXIe siècle. On trouvera dans la base de données GeoScan de plus amples informations sont disponibles. Morales, J.F., Song, T., Auerbach, A.D., and Wittkowski, K.M., 2008. Phenotyping genetic diseases using an extension of &#956;-scores for Multivariate Data. Statistical Applications in Genetics and Molecular Biology, 7: 1-18 DOI: 10.2202/1544-6115.1372 Wittkowski, K. M., Lee, E., Nussbaum, R., Chamian, F. N., & Krueger, J. G. (2004). Combining several ordinal measures in clinical studies. Statistics in Medicine, 23: 1579-1592. https://doi.org/10.1002/sim.1778."
      }}}
    }
  }},
  "gmd:distributionInfo": {"gmd:MD_Distribution":   {
    "gmd:distributionFormat": {"gmd:MD_Format":     {
      "gmd:name": {"gco:CharacterString":       {
        "@xmlns:gco": "http://www.isotc211.org/2005/gco",
        "#text": "SHP"
      }},
      "gmd:version": {"gco:CharacterString":       {
        "@xmlns:gco": "http://www.isotc211.org/2005/gco",
        "#text": "ESRI ArcGIS"
      }}
    }},
    "gmd:distributor":     [
      {"gmd:MD_Distributor": {"gmd:distributorContact": {"gmd:CI_ResponsibleParty":       {
        "gmd:individualName":         {
          "@xmlns:xsi": "http://www.w3.org/2001/XMLSchema-instance",
          "@xsi:type": "gmd:PT_FreeText_PropertyType",
          "gco:CharacterString":           {
            "@xmlns:gco": "http://www.isotc211.org/2005/gco",
            "#text": "Gavin Manson"
          },
          "gmd:PT_FreeText": {"gmd:textGroup": {"gmd:LocalisedCharacterString":           {
            "@locale": "#fra",
            "#text": "Gavin Manson"
          }}}
        },
        "gmd:organisationName":         {
          "@xmlns:xsi": "http://www.w3.org/2001/XMLSchema-instance",
          "@xsi:type": "gmd:PT_FreeText_PropertyType",
          "gco:CharacterString":           {
            "@xmlns:gco": "http://www.isotc211.org/2005/gco",
            "#text": "Government of Canada; Natural Resources Canada; Geological Survey of Canada - GSC Atlantique"
          },
          "gmd:PT_FreeText": {"gmd:textGroup": {"gmd:LocalisedCharacterString":           {
            "@locale": "#fra",
            "#text": "Gouvernement du Canada; Ressources naturelles Canada; Commission géologique du Canada - CGC Atlantique"
          }}}
        },
        "gmd:positionName":         {
          "@xmlns:xsi": "http://www.w3.org/2001/XMLSchema-instance",
          "@xsi:type": "gmd:PT_FreeText_PropertyType",
          "gco:CharacterString":           {
            "@xmlns:gco": "http://www.isotc211.org/2005/gco",
            "#text": "Coastal Geologist"
          },
          "gmd:PT_FreeText": {"gmd:textGroup": {"gmd:LocalisedCharacterString":           {
            "@locale": "#fra",
            "#text": "Géologue côtier"
          }}}
        },
        "gmd:contactInfo": {"gmd:CI_Contact":         {
          "gmd:phone": {"gmd:CI_Telephone": {"gmd:voice":           {
            "@xmlns:xsi": "http://www.w3.org/2001/XMLSchema-instance",
            "@xsi:type": "gmd:PT_FreeText_PropertyType",
            "gco:CharacterString":             {
              "@xmlns:gco": "http://www.isotc211.org/2005/gco",
              "#text": "voice; +01-902-426-3144"
            },
            "gmd:PT_FreeText": {"gmd:textGroup": {"gmd:LocalisedCharacterString":             {
              "@locale": "#fra",
              "#text": "voix; +01-902-426-3144"
            }}}
          }}},
          "gmd:address": {"gmd:CI_Address":           {
            "gmd:deliveryPoint":             {
              "@xmlns:xsi": "http://www.w3.org/2001/XMLSchema-instance",
              "@xsi:type": "PT_FreeText_PropertyType",
              "gco:CharacterString":               {
                "@xmlns:gco": "http://www.isotc211.org/2005/gco",
                "#text": "1 Challenger Drive"
              },
              "gmd:PT_FreeText": {"gmd:textGroup": {"gmd:LocalisedCharacterString":               {
                "@locale": "#fra",
                "#text": "1 Challenger Drive"
              }}}
            },
            "gmd:city":             {
              "@xmlns:xsi": "http://www.w3.org/2001/XMLSchema-instance",
              "@xsi:type": "PT_FreeText_PropertyType",
              "gco:CharacterString":               {
                "@xmlns:gco": "http://www.isotc211.org/2005/gco",
                "#text": "Dartmouth"
              },
              "gmd:PT_FreeText": {"gmd:textGroup": {"gmd:LocalisedCharacterString":               {
                "@locale": "#fra",
                "#text": "Dartmouth"
              }}}
            },
            "gmd:administrativeArea":             {
              "@xmlns:xsi": "http://www.w3.org/2001/XMLSchema-instance",
              "@xsi:type": "gmd:PT_FreeText_PropertyType",
              "gco:CharacterString":               {
                "@xmlns:gco": "http://www.isotc211.org/2005/gco",
                "#text": "Nova Scotia"
              },
              "gmd:PT_FreeText": {"gmd:textGroup": {"gmd:LocalisedCharacterString":               {
                "@locale": "#fra",
                "#text": "Nouvelle-Écosse"
              }}}
            },
            "gmd:country":             {
              "@xmlns:xsi": "http://www.w3.org/2001/XMLSchema-instance",
              "@xsi:type": "PT_FreeText_PropertyType",
              "gco:CharacterString":               {
                "@xmlns:gco": "http://www.isotc211.org/2005/gco",
                "#text": "Canada"
              },
              "gmd:PT_FreeText": {"gmd:textGroup": {"gmd:LocalisedCharacterString":               {
                "@locale": "#fra",
                "#text": "Canada"
              }}}
            },
            "gmd:electronicMailAddress":             {
              "@xmlns:xsi": "http://www.w3.org/2001/XMLSchema-instance",
              "@xsi:type": "PT_FreeText_PropertyType",
              "gco:CharacterString":               {
                "@xmlns:gco": "http://www.isotc211.org/2005/gco",
                "#text": "gavin.manson@canada.ca"
              },
              "gmd:PT_FreeText": {"gmd:textGroup": {"gmd:LocalisedCharacterString":               {
                "@locale": "#fra",
                "#text": "gavin.manson@canada.ca"
              }}}
            }
          }}
        }},
        "gmd:role": {"gmd:CI_RoleCode":         {
          "@codeList": "http://nap.geogratis.gc.ca/metadata/register/napMetadataRegister.xml#IC_90",
          "@codeListValue": "RI_412",
          "#text": "distributor; distributeur"
        }}
      }}}},
      {"gmd:MD_Distributor": {"gmd:distributorContact": {"gmd:CI_ResponsibleParty":       {
        "gmd:organisationName":         {
          "@xmlns:xsi": "http://www.w3.org/2001/XMLSchema-instance",
          "@xsi:type": "gmd:PT_FreeText_PropertyType",
          "gco:CharacterString":           {
            "@xmlns:gco": "http://www.isotc211.org/2005/gco",
            "#text": "Government of Canada; Natural Resources Canada; Geological Survey of Canada"
          },
          "gmd:PT_FreeText": {"gmd:textGroup": {"gmd:LocalisedCharacterString":           {
            "@locale": "#fra",
            "#text": "Gouvernement du Canada; Ressources naturelles Canada; Commission géologique du Canada"
          }}}
        },
        "gmd:contactInfo": {"gmd:CI_Contact": {"gmd:address": {"gmd:CI_Address": {"gmd:electronicMailAddress":         {
          "@xmlns:xsi": "http://www.w3.org/2001/XMLSchema-instance",
          "@xsi:type": "gmd:PT_FreeText_PropertyType",
          "gco:CharacterString":           {
            "@xmlns:gco": "http://www.isotc211.org/2005/gco",
            "#text": "nrcan.gsc-geosciencedata-donneesgeoscience-cgc.rncan@canada.ca"
          },
          "gmd:PT_FreeText": {"gmd:textGroup": {"gmd:LocalisedCharacterString":           {
            "@locale": "#fra",
            "#text": "nrcan.gsc-geosciencedata-donneesgeoscience-cgc.rncan@canada.ca"
          }}}
        }}}}},
        "gmd:role": {"gmd:CI_RoleCode":         {
          "@codeList": "http://nap.geogratis.gc.ca/metadata/register/napMetadataRegister.xml#IC_90",
          "@codeListValue": "RI_414",
          "#text": "pointOfContact; contact"
        }}
      }}}}
    ],
    "gmd:transferOptions": {"gmd:MD_DigitalTransferOptions":     {
      "gmd:transferSize": {"gco:Real":       {
        "@xmlns:gco": "http://www.isotc211.org/2005/gco",
        "#text": "274"
      }},
      "gmd:onLine":       [
                {
          "@xmlns:xlink": "http://www.w3.org/1999/xlink",
          "@xlink:role": "urn:xml:lang:fra-CAN",
          "gmd:CI_OnlineResource":           {
            "gmd:linkage": {"gmd:URL": "https://doi.org/10.4095/314669"},
            "gmd:protocol": {"gco:CharacterString":             {
              "@xmlns:gco": "http://www.isotc211.org/2005/gco",
              "#text": "HTTPS"
            }},
            "gmd:name":             {
              "@xmlns:xsi": "http://www.w3.org/2001/XMLSchema-instance",
              "@xsi:type": "gmd:PT_FreeText_PropertyType",
              "gco:CharacterString":               {
                "@xmlns:gco": "http://www.isotc211.org/2005/gco",
                "#text": "CanCoast Coastal Sensitivity Indices Version 2.5.6"
              },
              "gmd:PT_FreeText": {"gmd:textGroup": {"gmd:LocalisedCharacterString":               {
                "@locale": "#fra",
                "#text": "Base CanCoast sur les indices de sensibilité du littoral, version 2.5.6"
              }}}
            },
            "gmd:description":             {
              "@xmlns:xsi": "http://www.w3.org/2001/XMLSchema-instance",
              "@xsi:type": "gmd:PT_FreeText_PropertyType",
              "gco:CharacterString":               {
                "@xmlns:gco": "http://www.isotc211.org/2005/gco",
                "#text": "Dataset;HTML;eng"
              },
              "gmd:PT_FreeText": {"gmd:textGroup": {"gmd:LocalisedCharacterString":               {
                "@locale": "#fra",
                "#text": "Données;HTML;fra"
              }}}
            },
            "gmd:function": {"gmd:CI_OnLineFunctionCode":             {
              "@codeList": "http://nap.geogratis.gc.ca/metadata/register/napMetadataRegister.xml#IC_88",
              "@codeListValue": "RI_375",
              "#text": "download; téléchargement"
            }}
          }
        },
                {
          "@xmlns:xlink": "http://www.w3.org/1999/xlink",
          "@xlink:role": "urn:xml:lang:eng-CAN",
          "gmd:CI_OnlineResource":           {
            "gmd:linkage": {"gmd:URL": "https://doi.org/10.4095/314669"},
            "gmd:protocol": {"gco:CharacterString":             {
              "@xmlns:gco": "http://www.isotc211.org/2005/gco",
              "#text": "HTTPS"
            }},
            "gmd:name":             {
              "@xmlns:xsi": "http://www.w3.org/2001/XMLSchema-instance",
              "@xsi:type": "gmd:PT_FreeText_PropertyType",
              "gco:CharacterString":               {
                "@xmlns:gco": "http://www.isotc211.org/2005/gco",
                "#text": "Base CanCoast sur les indices de sensibilité du littoral, version 2.5.6"
              },
              "gmd:PT_FreeText": {"gmd:textGroup": {"gmd:LocalisedCharacterString":               {
                "@locale": "#fra",
                "#text": "CanCoast Coastal Sensitivity Indices Version 2.5.6"
              }}}
            },
            "gmd:description":             {
              "@xmlns:xsi": "http://www.w3.org/2001/XMLSchema-instance",
              "@xsi:type": "gmd:PT_FreeText_PropertyType",
              "gco:CharacterString":               {
                "@xmlns:gco": "http://www.isotc211.org/2005/gco",
                "#text": "Dataset;HTML;eng"
              },
              "gmd:PT_FreeText": {"gmd:textGroup": {"gmd:LocalisedCharacterString":               {
                "@locale": "#fra",
                "#text": "Données;HTML;eng"
              }}}
            },
            "gmd:function": {"gmd:CI_OnLineFunctionCode":             {
              "@codeList": "http://nap.geogratis.gc.ca/metadata/register/napMetadataRegister.xml#IC_88",
              "@codeListValue": "RI_375",
              "#text": "download; téléchargement"
            }}
          }
        }
      ]
    }}
  }},
  "gmd:dataQualityInfo": {"gmd:DQ_DataQuality":   {
    "gmd:scope": {"gmd:DQ_Scope": {"gmd:level": {"gmd:MD_ScopeCode":     {
      "@codeList": "http://nap.geogratis.gc.ca/metadata/register/napMetadataRegister.xml#IC_108",
      "@codeListValue": "RI_622",
      "#text": "dataset; jeuDonnées"
    }}}},
    "gmd:lineage": {"gmd:LI_Lineage":     {
      "gmd:statement":       {
        "@xmlns:xsi": "http://www.w3.org/2001/XMLSchema-instance",
        "@xsi:type": "gmd:PT_FreeText_PropertyType",
        "gco:CharacterString":         {
          "@xmlns:gco": "http://www.isotc211.org/2005/gco",
          "#text": "Process step no. 3 Generic process step - data source list Process step no. 1 Process step no. 4 Process step no. 2"
        },
        "gmd:PT_FreeText": {"gmd:textGroup": {"gmd:LocalisedCharacterString":         {
          "@locale": "#fra",
          "#text": "Étape de traitement no 3 Étape de traitement générique - liste des sources de données Étape de traitement no 1 Étape de traitement no 4 Étape de traitement no 2"
        }}}
      },
      "gmd:processStep":       [
        {"gmd:LI_ProcessStep":         {
          "gmd:description":           {
            "@xmlns:xsi": "http://www.w3.org/2001/XMLSchema-instance",
            "@xsi:type": "gmd:PT_FreeText_PropertyType",
            "gco:CharacterString":             {
              "@xmlns:gco": "http://www.isotc211.org/2005/gco",
              "#text": "Using ArcGIS, the early 21st century sensitivity was subtracted from the late 21st century sensitivity to calculate the projected change in sensitivity over the 21st century. See Supplemental Information for details."
            },
            "gmd:PT_FreeText": {"gmd:textGroup": {"gmd:LocalisedCharacterString":             {
              "@locale": "#fra",
              "#text": "Nous avons soustrait à l'aide du système ArcGIS, la sensibilité au début du XXIe siècle de celle de la fin du XXIe siècle pour calculer la variation prévue de la sensibilité au cours du XXIe siècle. On trouvera plus de détails dans les renseignements supplémentaires."
            }}}
          },
          "gmd:dateTime": {"gco:DateTime":           {
            "@xmlns:gco": "http://www.isotc211.org/2005/gco",
            "#text": "2019-05-01T00:00:00.0"
          }},
          "gmd:processor": {"gmd:CI_ResponsibleParty":           {
            "gmd:individualName":             {
              "@xmlns:xsi": "http://www.w3.org/2001/XMLSchema-instance",
              "@xsi:type": "gmd:PT_FreeText_PropertyType",
              "gco:CharacterString":               {
                "@xmlns:gco": "http://www.isotc211.org/2005/gco",
                "#text": "Gavin Manson"
              },
              "gmd:PT_FreeText": {"gmd:textGroup": {"gmd:LocalisedCharacterString":               {
                "@locale": "#fra",
                "#text": "Gavin Manson"
              }}}
            },
            "gmd:organisationName":             {
              "@xmlns:xsi": "http://www.w3.org/2001/XMLSchema-instance",
              "@xsi:type": "gmd:PT_FreeText_PropertyType",
              "gco:CharacterString":               {
                "@xmlns:gco": "http://www.isotc211.org/2005/gco",
                "#text": "Government of Canada; Natural Resources Canada; Geological Survey of Canada - GSC Atlantique"
              },
              "gmd:PT_FreeText": {"gmd:textGroup": {"gmd:LocalisedCharacterString":               {
                "@locale": "#fra",
                "#text": "Gouvernement du Canada; Ressources naturelles Canada; Commission géologique du Canada - CGC Atlantique"
              }}}
            },
            "gmd:positionName":             {
              "@xmlns:xsi": "http://www.w3.org/2001/XMLSchema-instance",
              "@xsi:type": "gmd:PT_FreeText_PropertyType",
              "gco:CharacterString":               {
                "@xmlns:gco": "http://www.isotc211.org/2005/gco",
                "#text": "Coastal Geologist"
              },
              "gmd:PT_FreeText": {"gmd:textGroup": {"gmd:LocalisedCharacterString":               {
                "@locale": "#fra",
                "#text": "Géologue côtier"
              }}}
            },
            "gmd:role": {"gmd:CI_RoleCode":             {
              "@codeList": "http://nap.geogratis.gc.ca/metadata/register/napMetadataRegister.xml#IC_90",
              "@codeListValue": "RI_416",
              "#text": "processor; traiteur"
            }}
          }},
          "gmd:source": {"gmd:LI_Source": {"gmd:description":           {
            "@xmlns:xsi": "http://www.w3.org/2001/XMLSchema-instance",
            "@xsi:type": "gmd:PT_FreeText_PropertyType",
            "gco:CharacterString":             {
              "@xmlns:gco": "http://www.isotc211.org/2005/gco",
              "#text": "See the generic process step for a list of data sources."
            },
            "gmd:PT_FreeText": {"gmd:textGroup": {"gmd:LocalisedCharacterString":             {
              "@locale": "#fra",
              "#text": "Voir l'étape de traitement générique pour une liste des sources de données."
            }}}
          }}}
        }},
        {"gmd:LI_ProcessStep":         {
          "gmd:description":           {
            "@xmlns:xsi": "http://www.w3.org/2001/XMLSchema-instance",
            "@xsi:type": "gmd:PT_FreeText_PropertyType",
            "gco:CharacterString":             {
              "@xmlns:gco": "http://www.isotc211.org/2005/gco",
              "#text": "This generic process step lists all the data sources used to create the dataset"
            },
            "gmd:PT_FreeText": {"gmd:textGroup": {"gmd:LocalisedCharacterString":             {
              "@locale": "#fra",
              "#text": "Cette étape de traitement générique dresse la liste de toutes les sources de données utilisées pour créer l'ensemble de données."
            }}}
          },
          "gmd:dateTime": {"gco:DateTime":           {
            "@xmlns:gco": "http://www.isotc211.org/2005/gco",
            "#text": "2019-05-01T00:00:00.0"
          }},
          "gmd:processor": {"gmd:CI_ResponsibleParty":           {
            "gmd:individualName":             {
              "@xmlns:xsi": "http://www.w3.org/2001/XMLSchema-instance",
              "@xsi:type": "gmd:PT_FreeText_PropertyType",
              "gco:CharacterString":               {
                "@xmlns:gco": "http://www.isotc211.org/2005/gco",
                "#text": "Gavin Manson"
              },
              "gmd:PT_FreeText": {"gmd:textGroup": {"gmd:LocalisedCharacterString":               {
                "@locale": "#fra",
                "#text": "Gavin Manson"
              }}}
            },
            "gmd:organisationName":             {
              "@xmlns:xsi": "http://www.w3.org/2001/XMLSchema-instance",
              "@xsi:type": "gmd:PT_FreeText_PropertyType",
              "gco:CharacterString":               {
                "@xmlns:gco": "http://www.isotc211.org/2005/gco",
                "#text": "Government of Canada; Natural Resources Canada; Geological Survey of Canada - GSC Atlantique"
              },
              "gmd:PT_FreeText": {"gmd:textGroup": {"gmd:LocalisedCharacterString":               {
                "@locale": "#fra",
                "#text": "Gouvernement du Canada; Ressources naturelles Canada; Commission géologique du Canada - CGC Atlantique"
              }}}
            },
            "gmd:positionName":             {
              "@xmlns:xsi": "http://www.w3.org/2001/XMLSchema-instance",
              "@xsi:type": "gmd:PT_FreeText_PropertyType",
              "gco:CharacterString":               {
                "@xmlns:gco": "http://www.isotc211.org/2005/gco",
                "#text": "Coastal Geologist"
              },
              "gmd:PT_FreeText": {"gmd:textGroup": {"gmd:LocalisedCharacterString":               {
                "@locale": "#fra",
                "#text": "Géologue côtier"
              }}}
            },
            "gmd:role": {"gmd:CI_RoleCode":             {
              "@codeList": "http://nap.geogratis.gc.ca/metadata/register/napMetadataRegister.xml#IC_90",
              "@codeListValue": "RI_416",
              "#text": "processor; traiteur"
            }}
          }},
          "gmd:source": {"gmd:LI_Source": {"gmd:description":           {
            "@xmlns:xsi": "http://www.w3.org/2001/XMLSchema-instance",
            "@xsi:type": "gmd:PT_FreeText_PropertyType",
            "gco:CharacterString":             {
              "@xmlns:gco": "http://www.isotc211.org/2005/gco",
              "#text": "CanCoast - Significant Wave Height Including Sea Ice Effects 1996-2005 Version 1.0 |- CanCoast - Significant Wave Height Including Sea Ice Effects 2090-2099 Version 1.0 |- CanCoast - Change In Sea Level 2006-2020 Version 1.0 |- CanCoast - Change In Sea Level 2006-2099 Version 1.0|- CanCoast - Coastal Materials Version 2.0 |- CanCoast - Ground Ice Version 1.0 |- CanCoast - Tidal Range Version 6.0 |- CanCoast - Backshore Slope Version 3.0 |- CanCoast Marine Shoreline Version 3.0"
            },
            "gmd:PT_FreeText": {"gmd:textGroup": {"gmd:LocalisedCharacterString":             {
              "@locale": "#fra",
              "#text": "CanCoast - Changemement de la hauteur moyenne des vagues significatives, et les effets de la glace de mer de 1995 à 2005, version 1.0 |- CanCoast - Changemement de la hauteur moyenne des vagues significatives, et les effets de la glace de mer de 2090 à 2099, version 1.0 |- CanCoast - Modification du niveau de la mer de 2006 à 2020, version 1.0 |- CanCoast - Modification du niveau de la mer de 2006 à 2099, version 1.0 |- CanCoast - Glaces de sol, version 1.0 |- CanCoast - Matériaux de zones côtières, version 2.0 |- CanCoast - Amplitude de marées, version 6.0 |- CanCoast - Pente de l'arrière-plage, version 3.0 |- CanCoast - Littoral maritime, version 3.0"
            }}}
          }}}
        }},
        {"gmd:LI_ProcessStep":         {
          "gmd:description":           {
            "@xmlns:xsi": "http://www.w3.org/2001/XMLSchema-instance",
            "@xsi:type": "gmd:PT_FreeText_PropertyType",
            "gco:CharacterString":             {
              "@xmlns:gco": "http://www.isotc211.org/2005/gco",
              "#text": "Using Python scripting in ArcGIS, the scores in the data sources were used to calculate an index of sensitivity in the early 21st century. See Supplemental Information for details."
            },
            "gmd:PT_FreeText": {"gmd:textGroup": {"gmd:LocalisedCharacterString":             {
              "@locale": "#fra",
              "#text": "Nous avons exécuté une macro Python dans ArcGIS pour calculer à l'aide des scores attribués dans les sources de données un indice de sensibilité pour le début du XXIe siècle. On trouvera plus de détails dans les renseignements supplémentaires."
            }}}
          },
          "gmd:dateTime": {"gco:DateTime":           {
            "@xmlns:gco": "http://www.isotc211.org/2005/gco",
            "#text": "2019-05-01T00:00:00.0"
          }},
          "gmd:processor": {"gmd:CI_ResponsibleParty":           {
            "gmd:individualName":             {
              "@xmlns:xsi": "http://www.w3.org/2001/XMLSchema-instance",
              "@xsi:type": "gmd:PT_FreeText_PropertyType",
              "gco:CharacterString":               {
                "@xmlns:gco": "http://www.isotc211.org/2005/gco",
                "#text": "Gavin Manson"
              },
              "gmd:PT_FreeText": {"gmd:textGroup": {"gmd:LocalisedCharacterString":               {
                "@locale": "#fra",
                "#text": "Gavin Manson"
              }}}
            },
            "gmd:organisationName":             {
              "@xmlns:xsi": "http://www.w3.org/2001/XMLSchema-instance",
              "@xsi:type": "gmd:PT_FreeText_PropertyType",
              "gco:CharacterString":               {
                "@xmlns:gco": "http://www.isotc211.org/2005/gco",
                "#text": "Government of Canada; Natural Resources Canada; Geological Survey of Canada - GSC Atlantique"
              },
              "gmd:PT_FreeText": {"gmd:textGroup": {"gmd:LocalisedCharacterString":               {
                "@locale": "#fra",
                "#text": "Gouvernement du Canada; Ressources naturelles Canada; Commission géologique du Canada - CGC Atlantique"
              }}}
            },
            "gmd:positionName":             {
              "@xmlns:xsi": "http://www.w3.org/2001/XMLSchema-instance",
              "@xsi:type": "gmd:PT_FreeText_PropertyType",
              "gco:CharacterString":               {
                "@xmlns:gco": "http://www.isotc211.org/2005/gco",
                "#text": "Coastal Geologist"
              },
              "gmd:PT_FreeText": {"gmd:textGroup": {"gmd:LocalisedCharacterString":               {
                "@locale": "#fra",
                "#text": "Géologue côtier"
              }}}
            },
            "gmd:role": {"gmd:CI_RoleCode":             {
              "@codeList": "http://nap.geogratis.gc.ca/metadata/register/napMetadataRegister.xml#IC_90",
              "@codeListValue": "RI_416",
              "#text": "processor; traiteur"
            }}
          }},
          "gmd:source": {"gmd:LI_Source": {"gmd:description":           {
            "@xmlns:xsi": "http://www.w3.org/2001/XMLSchema-instance",
            "@xsi:type": "gmd:PT_FreeText_PropertyType",
            "gco:CharacterString":             {
              "@xmlns:gco": "http://www.isotc211.org/2005/gco",
              "#text": "See the generic process step for a list of data sources."
            },
            "gmd:PT_FreeText": {"gmd:textGroup": {"gmd:LocalisedCharacterString":             {
              "@locale": "#fra",
              "#text": "Voir l'étape de traitement générique pour une liste des sources de données."
            }}}
          }}}
        }},
        {"gmd:LI_ProcessStep":         {
          "gmd:description":           {
            "@xmlns:xsi": "http://www.w3.org/2001/XMLSchema-instance",
            "@xsi:type": "gmd:PT_FreeText_PropertyType",
            "gco:CharacterString":             {
              "@xmlns:gco": "http://www.isotc211.org/2005/gco",
              "#text": "Using ArcGIS project tool, projected to decimal degrees in the NAD83 CSRS geographic coordinate system."
            },
            "gmd:PT_FreeText": {"gmd:textGroup": {"gmd:LocalisedCharacterString":             {
              "@locale": "#fra",
              "#text": "À l'aide de l'outil de projet d'ArcGIS, les données sont projetées en degrés décimaux dans le système de coordonnées géographiques du SCRS (NAD83)."
            }}}
          },
          "gmd:dateTime": {"gco:DateTime":           {
            "@xmlns:gco": "http://www.isotc211.org/2005/gco",
            "#text": "2019-05-01T00:00:00.0"
          }},
          "gmd:processor": {"gmd:CI_ResponsibleParty":           {
            "gmd:individualName":             {
              "@xmlns:xsi": "http://www.w3.org/2001/XMLSchema-instance",
              "@xsi:type": "gmd:PT_FreeText_PropertyType",
              "gco:CharacterString":               {
                "@xmlns:gco": "http://www.isotc211.org/2005/gco",
                "#text": "Gavin Manson"
              },
              "gmd:PT_FreeText": {"gmd:textGroup": {"gmd:LocalisedCharacterString":               {
                "@locale": "#fra",
                "#text": "Gavin Manson"
              }}}
            },
            "gmd:organisationName":             {
              "@xmlns:xsi": "http://www.w3.org/2001/XMLSchema-instance",
              "@xsi:type": "gmd:PT_FreeText_PropertyType",
              "gco:CharacterString":               {
                "@xmlns:gco": "http://www.isotc211.org/2005/gco",
                "#text": "Government of Canada; Natural Resources Canada; Geological Survey of Canada - GSC Atlantique"
              },
              "gmd:PT_FreeText": {"gmd:textGroup": {"gmd:LocalisedCharacterString":               {
                "@locale": "#fra",
                "#text": "Gouvernement du Canada; Ressources naturelles Canada; Commission géologique du Canada - CGC Atlantique"
              }}}
            },
            "gmd:positionName":             {
              "@xmlns:xsi": "http://www.w3.org/2001/XMLSchema-instance",
              "@xsi:type": "gmd:PT_FreeText_PropertyType",
              "gco:CharacterString":               {
                "@xmlns:gco": "http://www.isotc211.org/2005/gco",
                "#text": "Coastal Geologist"
              },
              "gmd:PT_FreeText": {"gmd:textGroup": {"gmd:LocalisedCharacterString":               {
                "@locale": "#fra",
                "#text": "Géologue côtier"
              }}}
            },
            "gmd:role": {"gmd:CI_RoleCode":             {
              "@codeList": "http://nap.geogratis.gc.ca/metadata/register/napMetadataRegister.xml#IC_90",
              "@codeListValue": "RI_416",
              "#text": "processor; traiteur"
            }}
          }},
          "gmd:source": {"gmd:LI_Source": {"gmd:description":           {
            "@xmlns:xsi": "http://www.w3.org/2001/XMLSchema-instance",
            "@xsi:type": "gmd:PT_FreeText_PropertyType",
            "gco:CharacterString":             {
              "@xmlns:gco": "http://www.isotc211.org/2005/gco",
              "#text": "See the generic process step for a list of data sources."
            },
            "gmd:PT_FreeText": {"gmd:textGroup": {"gmd:LocalisedCharacterString":             {
              "@locale": "#fra",
              "#text": "Voir l'étape de traitement générique pour une liste des sources de données."
            }}}
          }}}
        }},
        {"gmd:LI_ProcessStep":         {
          "gmd:description":           {
            "@xmlns:xsi": "http://www.w3.org/2001/XMLSchema-instance",
            "@xsi:type": "gmd:PT_FreeText_PropertyType",
            "gco:CharacterString":             {
              "@xmlns:gco": "http://www.isotc211.org/2005/gco",
              "#text": "Using Python scripting in ArcGIS, the scores in the data sources were used to calculate an index of sensitivity in the late 21st century. See Supplemental Information for details."
            },
            "gmd:PT_FreeText": {"gmd:textGroup": {"gmd:LocalisedCharacterString":             {
              "@locale": "#fra",
              "#text": "Nous avons exécuté une macro Python dans ArcGIS pour calculer à l'aide des scores attribués dans les sources de données un indice de sensibilité pour la fin du XXIe siècle. On trouvera plus de détails dans les renseignements supplémentaires."
            }}}
          },
          "gmd:dateTime": {"gco:DateTime":           {
            "@xmlns:gco": "http://www.isotc211.org/2005/gco",
            "#text": "2019-05-01T00:00:00.0"
          }},
          "gmd:processor": {"gmd:CI_ResponsibleParty":           {
            "gmd:individualName":             {
              "@xmlns:xsi": "http://www.w3.org/2001/XMLSchema-instance",
              "@xsi:type": "gmd:PT_FreeText_PropertyType",
              "gco:CharacterString":               {
                "@xmlns:gco": "http://www.isotc211.org/2005/gco",
                "#text": "Gavin Manson"
              },
              "gmd:PT_FreeText": {"gmd:textGroup": {"gmd:LocalisedCharacterString":               {
                "@locale": "#fra",
                "#text": "Gavin Manson"
              }}}
            },
            "gmd:organisationName":             {
              "@xmlns:xsi": "http://www.w3.org/2001/XMLSchema-instance",
              "@xsi:type": "gmd:PT_FreeText_PropertyType",
              "gco:CharacterString":               {
                "@xmlns:gco": "http://www.isotc211.org/2005/gco",
                "#text": "Government of Canada; Natural Resources Canada; Geological Survey of Canada - GSC Atlantique"
              },
              "gmd:PT_FreeText": {"gmd:textGroup": {"gmd:LocalisedCharacterString":               {
                "@locale": "#fra",
                "#text": "Gouvernement du Canada; Ressources naturelles Canada; Commission géologique du Canada - CGC Atlantique"
              }}}
            },
            "gmd:positionName":             {
              "@xmlns:xsi": "http://www.w3.org/2001/XMLSchema-instance",
              "@xsi:type": "gmd:PT_FreeText_PropertyType",
              "gco:CharacterString":               {
                "@xmlns:gco": "http://www.isotc211.org/2005/gco",
                "#text": "Coastal Geologist"
              },
              "gmd:PT_FreeText": {"gmd:textGroup": {"gmd:LocalisedCharacterString":               {
                "@locale": "#fra",
                "#text": "Géologue côtier"
              }}}
            },
            "gmd:role": {"gmd:CI_RoleCode":             {
              "@codeList": "http://nap.geogratis.gc.ca/metadata/register/napMetadataRegister.xml#IC_90",
              "@codeListValue": "RI_416",
              "#text": "processor; traiteur"
            }}
          }},
          "gmd:source": {"gmd:LI_Source": {"gmd:description":           {
            "@xmlns:xsi": "http://www.w3.org/2001/XMLSchema-instance",
            "@xsi:type": "gmd:PT_FreeText_PropertyType",
            "gco:CharacterString":             {
              "@xmlns:gco": "http://www.isotc211.org/2005/gco",
              "#text": "See the generic process step for a list of data sources."
            },
            "gmd:PT_FreeText": {"gmd:textGroup": {"gmd:LocalisedCharacterString":             {
              "@locale": "#fra",
              "#text": "Voir l'étape de traitement générique pour une liste des sources de données."
            }}}
          }}}
        }}
      ]
    }}
  }},
  "gmd:metadataMaintenance": {"gmd:MD_MaintenanceInformation": {"gmd:maintenanceAndUpdateFrequency": {"gmd:MD_MaintenanceFrequencyCode":   {
    "@codeList": "http://nap.geogratis.gc.ca/metadata/register/napMetadataRegister.xml#IC_102",
    "@codeListValue": "RI_540",
    "#text": "asNeeded; auBesoin"
  }}}},
  "geonet:info":   {
    "id": "7904",
    "schema": "iso19139.nap",
    "createDate": "2019-09-16T13:57:10",
    "changeDate": "2019-09-16T19:43:49",
    "isTemplate": "n",
    "title": [],
    "source": "Prod",
    "uuid": "a8b68ba4-c3d9-707f-a866-1aa53e7f0ae6",
    "isHarvested": "n",
    "popularity": "41",
    "rating": "0",
    "displayOrder": null,
    "isPublishedToAll": "true",
    "view": "true",
    "notify": "false",
    "download": "true",
    "dynamic": "true",
    "featured": "false",
    "ownername": "François",
    "valid_details":     [
            {
        "type": "schematron-rules-ec",
        "status":         {
          "#text": "\n        1\n        ",
          "ratio": "0/112"
        }
      },
            {
        "type": "xsd",
        "status":         {
          "#text": "\n        1\n        ",
          "ratio": []
        }
      }
    ],
    "valid": "1",
    "baseUrl": "https://test.gcgeo.gc.ca:443null",
    "locService": "/srv/en"
  }
}